{"version":"0.1.0","name":"solrand","instructions":[{"name":"createPool","accounts":[{"name":"authority","isMut":true,"isSigner":true},{"name":"pool","isMut":true,"isSigner":false},{"name":"feedAccount1","isMut":false,"isSigner":false},{"name":"feedAccount2","isMut":false,"isSigner":false},{"name":"feedAccount3","isMut":false,"isSigner":false},{"name":"feedAccount4","isMut":false,"isSigner":false},{"name":"feedAccount5","isMut":false,"isSigner":false},{"name":"feedAccount6","isMut":false,"isSigner":false},{"name":"feedAccount7","isMut":false,"isSigner":false},{"name":"feedAccount8","isMut":false,"isSigner":false},{"name":"systemProgram","isMut":false,"isSigner":false}],"args":[{"name":"poolId","type":"u64"},{"name":"duration","type":"i64"}]},{"name":"commitRand","accounts":[{"name":"authority","isMut":true,"isSigner":true},{"name":"pool","isMut":true,"isSigner":false},{"name":"newRand","isMut":true,"isSigner":false},{"name":"systemProgram","isMut":false,"isSigner":false}],"args":[{"name":"commit","type":{"array":["u8",32]}}]},{"name":"loadRand","accounts":[{"name":"authority","isMut":false,"isSigner":true},{"name":"pool","isMut":false,"isSigner":false},{"name":"curRand","isMut":true,"isSigner":false},{"name":"feedAccount1","isMut":false,"isSigner":false},{"name":"feedAccount2","isMut":false,"isSigner":false},{"name":"feedAccount3","isMut":false,"isSigner":false},{"name":"feedAccount4","isMut":false,"isSigner":false},{"name":"feedAccount5","isMut":false,"isSigner":false},{"name":"feedAccount6","isMut":false,"isSigner":false},{"name":"feedAccount7","isMut":false,"isSigner":false},{"name":"feedAccount8","isMut":false,"isSigner":false},{"name":"systemProgram","isMut":false,"isSigner":false}],"args":[{"name":"randId","type":"u64"}]},{"name":"revealRand","accounts":[{"name":"authority","isMut":false,"isSigner":true},{"name":"pool","isMut":false,"isSigner":false},{"name":"curRand","isMut":true,"isSigner":false},{"name":"systemProgram","isMut":false,"isSigner":false}],"args":[{"name":"randId","type":"u64"},{"name":"sec","type":{"array":["u8",32]}}]},{"name":"closeRand","accounts":[{"name":"authority","isMut":false,"isSigner":true},{"name":"pool","isMut":false,"isSigner":false},{"name":"curRand","isMut":true,"isSigner":false},{"name":"systemProgram","isMut":false,"isSigner":false}],"args":[{"name":"randId","type":"u64"}]}],"accounts":[{"name":"Pool","type":{"kind":"struct","fields":[{"name":"poolId","type":"u64"},{"name":"authority","type":"publicKey"},{"name":"minDuration","type":"i64"},{"name":"length","type":"u64"},{"name":"feedAccount1","type":"publicKey"},{"name":"feedAccount2","type":"publicKey"},{"name":"feedAccount3","type":"publicKey"},{"name":"feedAccount4","type":"publicKey"},{"name":"feedAccount5","type":"publicKey"},{"name":"feedAccount6","type":"publicKey"},{"name":"feedAccount7","type":"publicKey"},{"name":"feedAccount8","type":"publicKey"}]}},{"name":"Rand","type":{"kind":"struct","fields":[{"name":"commitTime","type":"i64"},{"name":"loadTime","type":"i64"},{"name":"commit","type":{"array":["u8",32]}},{"name":"seed","type":{"array":["u8",32]}},{"name":"rands","type":{"array":["u32",8]}},{"name":"status","type":"u8"}]}}],"events":[{"name":"DidCommit","fields":[{"name":"commitTime","type":"i64","index":false},{"name":"randId","type":"u64","index":false},{"name":"poolId","type":"u64","index":false},{"name":"commit","type":{"array":["u8",32]},"index":false}]},{"name":"DidLoad","fields":[{"name":"randId","type":"u64","index":false},{"name":"loadTime","type":"i64","index":false},{"name":"seed1","type":"i64","index":false},{"name":"seed2","type":"i64","index":false},{"name":"seed3","type":"i64","index":false},{"name":"seed4","type":"i64","index":false},{"name":"seed","type":{"array":["u8",32]},"index":false}]},{"name":"DidReveal","fields":[{"name":"randId","type":"u64","index":false},{"name":"revealTime","type":"i64","index":false},{"name":"sec","type":{"array":["u8",32]},"index":false},{"name":"rands","type":{"array":["u32",8]},"index":false}]},{"name":"DidClose","fields":[{"name":"randId","type":"u64","index":false},{"name":"closeTime","type":"i64","index":false}]}]}